<annotation>
	<folder>bad_peaches</folder>
	<filename>7.png</filename>
	<path>C:\Users\QINGYU\Desktop\datasets\newDatasets\peach\bad_peaches\7.png</path>
	<source>
		<database>Unknown</database>
	</source>
	<size>
		<width>741</width>
		<height>722</height>
		<depth>3</depth>
	</size>
	<segmented>0</segmented>
	<object>
		<name>peach_C</name>
		<pose>Unspecified</pose>
		<truncated>1</truncated>
		<difficult>0</difficult>
		<bndbox>
			<xmin>36</xmin>
			<ymin>54</ymin>
			<xmax>727</xmax>
			<ymax>722</ymax>
		</bndbox>
	</object>
</annotation>
